{
  "pokedexID": "868",
  "species": "Milcery",
  "events": [
    {
      "pokemon": {
        "name": " マホミル  ♀",
        "pokeball": "cherishball",
        "shiny": false,
        "level": 5,
        "OT": "ポケセン",
        "ID": "201101",
        "ability": "Sweet Veil",
        "item": "Ribbon Sweet",
        "pokemonDescription": " Nature.Date of Receiving Pokï¿½mon Center. Apparently had a fateful encounter at Lv. 5",
        "moves": [
          "Celebrate",
          "Last Resort",
          "Entrainment",
          "Attract"
        ]
      },
      "event": {
        "description": "Pokémon Center Birthday Distribution",
        "type": "In-Life",
        "location": "Japan",
        "startDate": "1 November 2020",
        "endDate": "31 October 2021",
        "gamesAvailable": "Sword, Shield"
      }
    },
    {
      "pokemon": {
        "name": " マホミル  ♀",
        "pokeball": "cherishball",
        "shiny": false,
        "level": 5,
        "OT": "ポケセン",
        "ID": "201101",
        "ability": "Sweet Veil",
        "item": "Star Sweet",
        "pokemonDescription": " Nature.Date of Receiving Pokï¿½mon Center. Apparently had a fateful encounter at Lv. 5",
        "moves": [
          "Celebrate",
          "Last Resort",
          "Entrainment",
          "Attract"
        ]
      },
      "event": {
        "description": "Pokémon Center Birthday Distribution",
        "type": "In-Life",
        "location": "Japan",
        "startDate": "1 November 2020",
        "endDate": "31 October 2021",
        "gamesAvailable": "Sword, Shield"
      }
    },
    {
      "pokemon": {
        "name": " Milcery  ♀",
        "pokeball": "cherishball",
        "shiny": false,
        "level": 5,
        "OT": "PCSG",
        "ID": "201101",
        "ability": "Sweet Veil",
        "item": "Ribbon Sweet",
        "pokemonDescription": " Nature.Date of Receiving Pokï¿½mon Center. Apparently had a fateful encounter at Lv. 5",
        "moves": [
          "Celebrate",
          "Last Resort",
          "Entrainment",
          "Attract"
        ]
      },
      "event": {
        "description": "Pokémon Center Birthday Distribution",
        "type": "In-Life",
        "location": "Singapore",
        "startDate": "1 November 2020",
        "endDate": "31 October 2021",
        "gamesAvailable": "Sword, Shield"
      }
    },
    {
      "pokemon": {
        "name": " Milcery  ♀",
        "pokeball": "cherishball",
        "shiny": false,
        "level": 5,
        "OT": "PCSG;",
        "ID": "201101",
        "ability": "Sweet Veil",
        "item": "Star Sweet",
        "pokemonDescription": " Nature.Date of Receiving Pokï¿½mon Center. Apparently had a fateful encounter at Lv. 5",
        "moves": [
          "Celebrate",
          "Last Resort",
          "Entrainment",
          "Attract"
        ]
      },
      "event": {
        "description": "Pokémon Center Birthday Distribution",
        "type": "In-Life",
        "location": "Singapore",
        "startDate": "1 November 2020",
        "endDate": "31 October 2021",
        "gamesAvailable": "Sword, Shield"
      }
    }
  ]
}